hikconnect/__init__.py
hikconnect/api.py
hikconnect/exceptions.py
hikconnect-1.2.1.dist-info/METADATA
hikconnect-1.2.1.dist-info/WHEEL
hikconnect-1.2.1.dist-info/RECORD
